argocli/__init__.py
argocli/cli/main.py
argocli/commands/command.py
argocli/commands/workflow/__init__.py
argocli/commands/workflow/browse.py
argocli/commands/workflow/list.py
argocli/commands/workflow/status.py
argocli/commands/workflow/view.py
argocli/core/client.py
argocli-0.4.0.dist-info/licenses/LICENSE
argocli-0.4.0.dist-info/METADATA
argocli-0.4.0.dist-info/WHEEL
argocli-0.4.0.dist-info/entry_points.txt
argocli-0.4.0.dist-info/top_level.txt
argocli-0.4.0.dist-info/RECORD
