Metadata-Version: 2.4
Name: argocli
Version: 0.4.0
Summary: A command-line interface for Argo Workflows
Requires-Python: >=3.12
License-File: LICENSE
Requires-Dist: cac-core>=0.5.1
Requires-Dist: packaging>=25.0
Requires-Dist: requests>=2.32.4
Dynamic: license-file
